{
  "nodes": [
    {
      "id": "n418",
      "label": "Jobsti"
    },
    {
      "id": "n417",
      "label": "Goldman60"
    },
    {
      "id": "n419",
      "label": "kolinkrewinkel"
    },
    {
      "id": "n414",
      "label": "rjVapes"
    },
    {
      "id": "n413",
      "label": "graywolf336"
    },
    {
      "id": "n416",
      "label": "javaguy78"
    },
    {
      "id": "n360",
      "label": "kezz101"
    },
    {
      "id": "n415",
      "label": "B2OJustin"
    },
    {
      "id": "n410",
      "label": "somaticstudios"
    },
    {
      "id": "n412",
      "label": "NinjaWolf"
    },
    {
      "id": "n411",
      "label": "eueln"
    },
    {
      "id": "n211",
      "label": "filbert66"
    },
    {
      "id": "n358",
      "label": "jedediah"
    },
    {
      "id": "n212",
      "label": "Zidane"
    },
    {
      "id": "n359",
      "label": "jamietech"
    },
    {
      "id": "n213",
      "label": "burgerkiller"
    },
    {
      "id": "n214",
      "label": "weja"
    },
    {
      "id": "n210",
      "label": "spydercanopus"
    },
    {
      "id": "n219",
      "label": "Wolf480pl"
    },
    {
      "id": "n350",
      "label": "keybordpiano459"
    },
    {
      "id": "n351",
      "label": "Xephi"
    },
    {
      "id": "n352",
      "label": "Azenet"
    },
    {
      "id": "n353",
      "label": "thefishlive"
    },
    {
      "id": "n215",
      "label": "andrewmcwatters"
    },
    {
      "id": "n354",
      "label": "creeperkit"
    },
    {
      "id": "n216",
      "label": "Pwn9"
    },
    {
      "id": "n355",
      "label": "Ranzdo"
    },
    {
      "id": "n217",
      "label": "rtcabooservb"
    },
    {
      "id": "n356",
      "label": "Eimref"
    },
    {
      "id": "n218",
      "label": "troed"
    },
    {
      "id": "n357",
      "label": "JakeShirley"
    },
    {
      "id": "n409",
      "label": "Zarius"
    },
    {
      "id": "n408",
      "label": "dreadiscool"
    },
    {
      "id": "n407",
      "label": "sternmin8or"
    },
    {
      "id": "n406",
      "label": "gravitythief"
    },
    {
      "id": "n405",
      "label": "nicatronTg"
    },
    {
      "id": "n404",
      "label": "Supertt007"
    },
    {
      "id": "n403",
      "label": "stuntguy3000"
    },
    {
      "id": "n402",
      "label": "navarr"
    },
    {
      "id": "n401",
      "label": "HappyIsFree"
    },
    {
      "id": "n400",
      "label": "iEvolive"
    },
    {
      "id": "n202",
      "label": "Drakia"
    },
    {
      "id": "n349",
      "label": "pruby"
    },
    {
      "id": "n203",
      "label": "raymanic13"
    },
    {
      "id": "n200",
      "label": "deathmarine"
    },
    {
      "id": "n347",
      "label": "zerg960"
    },
    {
      "id": "n201",
      "label": "spetznack"
    },
    {
      "id": "n348",
      "label": "AlexHart"
    },
    {
      "id": "n341",
      "label": "stirante"
    },
    {
      "id": "n342",
      "label": "psycowithespn"
    },
    {
      "id": "n208",
      "label": "tehbeard"
    },
    {
      "id": "n209",
      "label": "MrInfro"
    },
    {
      "id": "n340",
      "label": "SagaciousZed"
    },
    {
      "id": "n206",
      "label": "garbagemule"
    },
    {
      "id": "n345",
      "label": "thvortex"
    },
    {
      "id": "n207",
      "label": "t7seven7t"
    },
    {
      "id": "n346",
      "label": "seifpic"
    },
    {
      "id": "n204",
      "label": "khobbits"
    },
    {
      "id": "n343",
      "label": "L8D"
    },
    {
      "id": "n205",
      "label": "TehRealMayhem"
    },
    {
      "id": "n344",
      "label": "EvilPeanut"
    },
    {
      "id": "n436",
      "label": "Tobseb"
    },
    {
      "id": "n435",
      "label": "ty2u"
    },
    {
      "id": "n438",
      "label": "NodinChan"
    },
    {
      "id": "n437",
      "label": "yoo2001818"
    },
    {
      "id": "n439",
      "label": "TehRainbowGuy"
    },
    {
      "id": "n430",
      "label": "antoligy"
    },
    {
      "id": "n432",
      "label": "jb-aero"
    },
    {
      "id": "n431",
      "label": "AmoebaMan"
    },
    {
      "id": "n434",
      "label": "hoqhuuep"
    },
    {
      "id": "n433",
      "label": "coaster3000"
    },
    {
      "id": "n230",
      "label": "cnaude"
    },
    {
      "id": "n231",
      "label": "sorken"
    },
    {
      "id": "n232",
      "label": "GrayShine"
    },
    {
      "id": "n233",
      "label": "meem1029"
    },
    {
      "id": "n336",
      "label": "FearTheElite"
    },
    {
      "id": "n234",
      "label": "Dubi01"
    },
    {
      "id": "n337",
      "label": "bloodmc"
    },
    {
      "id": "n235",
      "label": "Hactarus"
    },
    {
      "id": "n338",
      "label": "khenriks"
    },
    {
      "id": "n236",
      "label": "Noobik42RUS"
    },
    {
      "id": "n339",
      "label": "Black-Hole"
    },
    {
      "id": "n237",
      "label": "craftycreeper"
    },
    {
      "id": "n332",
      "label": "MisterFix"
    },
    {
      "id": "n238",
      "label": "Jereq"
    },
    {
      "id": "n333",
      "label": "meiskam"
    },
    {
      "id": "n239",
      "label": "YoFuzzy3"
    },
    {
      "id": "n334",
      "label": "gomeow"
    },
    {
      "id": "n335",
      "label": "Lymia"
    },
    {
      "id": "n330",
      "label": "cexikitin"
    },
    {
      "id": "n331",
      "label": "avatarDr"
    },
    {
      "id": "n427",
      "label": "j1i"
    },
    {
      "id": "n426",
      "label": "tjnome"
    },
    {
      "id": "n425",
      "label": "mushroomhostage"
    },
    {
      "id": "n424",
      "label": "JadenKorr"
    },
    {
      "id": "n429",
      "label": "glider521al"
    },
    {
      "id": "n428",
      "label": "cyberkitsune"
    },
    {
      "id": "n423",
      "label": "ams2990"
    },
    {
      "id": "n422",
      "label": "Jckf"
    },
    {
      "id": "n421",
      "label": "Deadlock989"
    },
    {
      "id": "n420",
      "label": "FearThe1337"
    },
    {
      "id": "n220",
      "label": "terry90"
    },
    {
      "id": "n221",
      "label": "nossr50"
    },
    {
      "id": "n329",
      "label": "wizjany"
    },
    {
      "id": "n224",
      "label": "PitBull2709"
    },
    {
      "id": "n327",
      "label": "TriPhoenix"
    },
    {
      "id": "n225",
      "label": "Va1k"
    },
    {
      "id": "n328",
      "label": "ZNickq"
    },
    {
      "id": "n222",
      "label": "Nightgunner5"
    },
    {
      "id": "n325",
      "label": "kingjan1999"
    },
    {
      "id": "n223",
      "label": "wside420"
    },
    {
      "id": "n326",
      "label": "QuarterAnimal"
    },
    {
      "id": "n228",
      "label": "Abuz"
    },
    {
      "id": "n323",
      "label": "Lrns123"
    },
    {
      "id": "n229",
      "label": "Mineb0b"
    },
    {
      "id": "n324",
      "label": "andrepl"
    },
    {
      "id": "n226",
      "label": "LegendaryDevastation"
    },
    {
      "id": "n321",
      "label": "Verficon"
    },
    {
      "id": "n227",
      "label": "Pantheon5"
    },
    {
      "id": "n322",
      "label": "pdelvo"
    },
    {
      "id": "n320",
      "label": "lukegb"
    },
    {
      "id": "n453",
      "label": "Warpten"
    },
    {
      "id": "n454",
      "label": "Janmm14"
    },
    {
      "id": "n455",
      "label": "mooman219"
    },
    {
      "id": "n456",
      "label": "uweenukr"
    },
    {
      "id": "n450",
      "label": "ftbastler"
    },
    {
      "id": "n451",
      "label": "mrmag518"
    },
    {
      "id": "n452",
      "label": "skipperguy12"
    },
    {
      "id": "n457",
      "label": "Streammz"
    },
    {
      "id": "n311",
      "label": "D4rKDeagle"
    },
    {
      "id": "n310",
      "label": "tobiyas"
    },
    {
      "id": "n313",
      "label": "jordonus"
    },
    {
      "id": "n312",
      "label": "p000ison"
    },
    {
      "id": "n315",
      "label": "Acrobot"
    },
    {
      "id": "n314",
      "label": "UncleNinja"
    },
    {
      "id": "n317",
      "label": "Algent"
    },
    {
      "id": "n316",
      "label": "kellerkindt"
    },
    {
      "id": "n319",
      "label": "TomyLobo"
    },
    {
      "id": "n318",
      "label": "timvisee"
    },
    {
      "id": "n444",
      "label": "skyforce77"
    },
    {
      "id": "n445",
      "label": "cowsook"
    },
    {
      "id": "n442",
      "label": "netherfoam"
    },
    {
      "id": "n443",
      "label": "superpeanut911"
    },
    {
      "id": "n440",
      "label": "Alex-Bond"
    },
    {
      "id": "n441",
      "label": "selfservice0"
    },
    {
      "id": "n448",
      "label": "CraftThatBlock"
    },
    {
      "id": "n449",
      "label": "KoetseJ"
    },
    {
      "id": "n446",
      "label": "beaucoralk"
    },
    {
      "id": "n447",
      "label": "igniansoft"
    },
    {
      "id": "n302",
      "label": "tomsik68"
    },
    {
      "id": "n301",
      "label": "dejiplus"
    },
    {
      "id": "n300",
      "label": "Zetaeta"
    },
    {
      "id": "n306",
      "label": "Jessy1237"
    },
    {
      "id": "n305",
      "label": "nitnelave"
    },
    {
      "id": "n304",
      "label": "mastershake71"
    },
    {
      "id": "n303",
      "label": "THDigi"
    },
    {
      "id": "n309",
      "label": "imjake9"
    },
    {
      "id": "n308",
      "label": "mcunha"
    },
    {
      "id": "n307",
      "label": "johnoliverdriscoll"
    },
    {
      "id": "n299",
      "label": "7H3LaughingMan"
    },
    {
      "id": "n297",
      "label": "AStevensTaylor"
    },
    {
      "id": "n298",
      "label": "DeltaWhy"
    },
    {
      "id": "n295",
      "label": "devcompl"
    },
    {
      "id": "n296",
      "label": "attrib"
    },
    {
      "id": "n92",
      "label": "me4502"
    },
    {
      "id": "n91",
      "label": "rrama"
    },
    {
      "id": "n90",
      "label": "main--"
    },
    {
      "id": "n96",
      "label": "McSebi96"
    },
    {
      "id": "n95",
      "label": "Fliego"
    },
    {
      "id": "n94",
      "label": "jazzman170"
    },
    {
      "id": "n93",
      "label": "JamesNorris"
    },
    {
      "id": "n99",
      "label": "Njol"
    },
    {
      "id": "n98",
      "label": "andrewkm"
    },
    {
      "id": "n97",
      "label": "NemDiggers"
    },
    {
      "id": "n288",
      "label": "Resistance"
    },
    {
      "id": "n289",
      "label": "marcosds13"
    },
    {
      "id": "n284",
      "label": "Pentarctagon"
    },
    {
      "id": "n285",
      "label": "LordRalex"
    },
    {
      "id": "n286",
      "label": "krinsdeath"
    },
    {
      "id": "n287",
      "label": "petercoughlin"
    },
    {
      "id": "n292",
      "label": "AgroTemp"
    },
    {
      "id": "n291",
      "label": "ZephireNZ"
    },
    {
      "id": "n294",
      "label": "VoidWhisperer"
    },
    {
      "id": "n293",
      "label": "pqqqqq"
    },
    {
      "id": "n290",
      "label": "flatbmx"
    },
    {
      "id": "n1",
      "label": "amaranth"
    },
    {
      "id": "n0",
      "label": "Darkhand81"
    },
    {
      "id": "n5",
      "label": "BloodShura"
    },
    {
      "id": "n4",
      "label": "EdGruberman"
    },
    {
      "id": "n3",
      "label": "EvilSeph"
    },
    {
      "id": "n2",
      "label": "feildmaster"
    },
    {
      "id": "n9",
      "label": "sharkiller"
    },
    {
      "id": "n8",
      "label": "Wolvereness"
    },
    {
      "id": "n7",
      "label": "credomane"
    },
    {
      "id": "n6",
      "label": "grum"
    },
    {
      "id": "n397",
      "label": "urndel"
    },
    {
      "id": "n396",
      "label": "Arkel"
    },
    {
      "id": "n395",
      "label": "jugglingnutcase"
    },
    {
      "id": "n394",
      "label": "dualspiral"
    },
    {
      "id": "n399",
      "label": "Iaccidentally"
    },
    {
      "id": "n398",
      "label": "Jell-E"
    },
    {
      "id": "n259",
      "label": "ePixel"
    },
    {
      "id": "n258",
      "label": "Sp0ng3b0b"
    },
    {
      "id": "n257",
      "label": "tips48"
    },
    {
      "id": "n256",
      "label": "LimeByte"
    },
    {
      "id": "n255",
      "label": "ChinChangYang"
    },
    {
      "id": "n254",
      "label": "tnt"
    },
    {
      "id": "n253",
      "label": "Hidendra"
    },
    {
      "id": "n252",
      "label": "JonathanGecko"
    },
    {
      "id": "n251",
      "label": "lazertester"
    },
    {
      "id": "n260",
      "label": "javoris767"
    },
    {
      "id": "n261",
      "label": "t00thpick1"
    },
    {
      "id": "n384",
      "label": "Lynxy"
    },
    {
      "id": "n383",
      "label": "kukelekuuk00"
    },
    {
      "id": "n386",
      "label": "TheCryoknight"
    },
    {
      "id": "n385",
      "label": "Xaymar"
    },
    {
      "id": "n388",
      "label": "lenis0012"
    },
    {
      "id": "n249",
      "label": "drtshock"
    },
    {
      "id": "n387",
      "label": "Silthus"
    },
    {
      "id": "n248",
      "label": "cheatmasterbw"
    },
    {
      "id": "n389",
      "label": "ase34"
    },
    {
      "id": "n245",
      "label": "tambry"
    },
    {
      "id": "n244",
      "label": "Nikecow"
    },
    {
      "id": "n247",
      "label": "fread2281"
    },
    {
      "id": "n246",
      "label": "zeshan321"
    },
    {
      "id": "n241",
      "label": "salaman"
    },
    {
      "id": "n240",
      "label": "RobotoRaccoon"
    },
    {
      "id": "n243",
      "label": "xfloh22"
    },
    {
      "id": "n242",
      "label": "rafaskb"
    },
    {
      "id": "n250",
      "label": "Fronix"
    },
    {
      "id": "n390",
      "label": "xouxoux"
    },
    {
      "id": "n391",
      "label": "yoft"
    },
    {
      "id": "n392",
      "label": "kitskub"
    },
    {
      "id": "n393",
      "label": "Crunkle"
    },
    {
      "id": "n379",
      "label": "robin0van0der0v"
    },
    {
      "id": "n378",
      "label": "eimref"
    },
    {
      "id": "n377",
      "label": "R3creat3-dev"
    },
    {
      "id": "n376",
      "label": "dannycrafts"
    },
    {
      "id": "n375",
      "label": "cole2sworld"
    },
    {
      "id": "n374",
      "label": "MyPictures"
    },
    {
      "id": "n373",
      "label": "Unh0lyTigg"
    },
    {
      "id": "n372",
      "label": "mintplant"
    },
    {
      "id": "n276",
      "label": "aikar"
    },
    {
      "id": "n275",
      "label": "Age007"
    },
    {
      "id": "n274",
      "label": "milkywayz"
    },
    {
      "id": "n273",
      "label": "iRzilla"
    },
    {
      "id": "n279",
      "label": "Drakomord"
    },
    {
      "id": "n278",
      "label": "fisherman77"
    },
    {
      "id": "n277",
      "label": "Scyntrus"
    },
    {
      "id": "n282",
      "label": "ruan942"
    },
    {
      "id": "n283",
      "label": "ThatBox"
    },
    {
      "id": "n280",
      "label": "xxCoderforlife"
    },
    {
      "id": "n281",
      "label": "diamondo25"
    },
    {
      "id": "n381",
      "label": "Icyene"
    },
    {
      "id": "n382",
      "label": "rmsy"
    },
    {
      "id": "n380",
      "label": "ausbin"
    },
    {
      "id": "n366",
      "label": "thinkofdeath"
    },
    {
      "id": "n365",
      "label": "ST-DDT"
    },
    {
      "id": "n368",
      "label": "GravelSocks"
    },
    {
      "id": "n367",
      "label": "remixz"
    },
    {
      "id": "n362",
      "label": "jis2507"
    },
    {
      "id": "n361",
      "label": "defek7"
    },
    {
      "id": "n364",
      "label": "duckdoom5"
    },
    {
      "id": "n363",
      "label": "Hellsing"
    },
    {
      "id": "n263",
      "label": "iksDeeh-"
    },
    {
      "id": "n262",
      "label": "DwDMadMac"
    },
    {
      "id": "n265",
      "label": "thejfx"
    },
    {
      "id": "n264",
      "label": "RingOfStorms"
    },
    {
      "id": "n267",
      "label": "1n5aN1aC"
    },
    {
      "id": "n266",
      "label": "StarTux"
    },
    {
      "id": "n369",
      "label": "b1naryth1ef"
    },
    {
      "id": "n269",
      "label": "Kaan2106"
    },
    {
      "id": "n268",
      "label": "Cogito"
    },
    {
      "id": "n270",
      "label": "slipcor"
    },
    {
      "id": "n271",
      "label": "modwizcode"
    },
    {
      "id": "n272",
      "label": "Lexicality"
    },
    {
      "id": "n370",
      "label": "storm345"
    },
    {
      "id": "n371",
      "label": "W1ndwaker"
    },
    {
      "id": "n41",
      "label": "GuntherDW"
    },
    {
      "id": "n40",
      "label": "Seborg99"
    },
    {
      "id": "n172",
      "label": "LiLChris"
    },
    {
      "id": "n45",
      "label": "Runemoro"
    },
    {
      "id": "n173",
      "label": "Jadedwolf"
    },
    {
      "id": "n44",
      "label": "nallar"
    },
    {
      "id": "n170",
      "label": "nkrecklow"
    },
    {
      "id": "n43",
      "label": "rehv"
    },
    {
      "id": "n171",
      "label": "killerhunt0"
    },
    {
      "id": "n42",
      "label": "YinScape"
    },
    {
      "id": "n166",
      "label": "aaomidi"
    },
    {
      "id": "n48",
      "label": "Tux2"
    },
    {
      "id": "n165",
      "label": "AraFTWxD"
    },
    {
      "id": "n49",
      "label": "SuperSpyTX"
    },
    {
      "id": "n164",
      "label": "lemon42"
    },
    {
      "id": "n46",
      "label": "md-5"
    },
    {
      "id": "n163",
      "label": "ZachBora"
    },
    {
      "id": "n47",
      "label": "mbax"
    },
    {
      "id": "n169",
      "label": "SkeletonGamer"
    },
    {
      "id": "n168",
      "label": "xsonarx"
    },
    {
      "id": "n167",
      "label": "HighlifeTTU"
    },
    {
      "id": "n30",
      "label": "aadnk"
    },
    {
      "id": "n180",
      "label": "holic"
    },
    {
      "id": "n181",
      "label": "Zachar543"
    },
    {
      "id": "n32",
      "label": "Bestle"
    },
    {
      "id": "n182",
      "label": "GaggleBit"
    },
    {
      "id": "n31",
      "label": "mrapple"
    },
    {
      "id": "n183",
      "label": "UltraFaceguy"
    },
    {
      "id": "n34",
      "label": "obnoxint"
    },
    {
      "id": "n184",
      "label": "WoodenAxe"
    },
    {
      "id": "n33",
      "label": "TheDgtl"
    },
    {
      "id": "n175",
      "label": "PvM-Iain"
    },
    {
      "id": "n35",
      "label": "Ribesg"
    },
    {
      "id": "n174",
      "label": "worstboy32"
    },
    {
      "id": "n36",
      "label": "krisdestruction"
    },
    {
      "id": "n177",
      "label": "escortkeel"
    },
    {
      "id": "n37",
      "label": "h31ix"
    },
    {
      "id": "n176",
      "label": "Joeaniator1"
    },
    {
      "id": "n38",
      "label": "BangL"
    },
    {
      "id": "n179",
      "label": "Kiskae"
    },
    {
      "id": "n39",
      "label": "xZise"
    },
    {
      "id": "n178",
      "label": "aufdemrand"
    },
    {
      "id": "n23",
      "label": "Sleaker"
    },
    {
      "id": "n194",
      "label": "TerrorBite"
    },
    {
      "id": "n22",
      "label": "HenryLoenwind"
    },
    {
      "id": "n195",
      "label": "sk89q"
    },
    {
      "id": "n21",
      "label": "Bone008"
    },
    {
      "id": "n192",
      "label": "nala3"
    },
    {
      "id": "n20",
      "label": "jrtc27"
    },
    {
      "id": "n193",
      "label": "Nomy"
    },
    {
      "id": "n190",
      "label": "pdinklag"
    },
    {
      "id": "n191",
      "label": "akrieger"
    },
    {
      "id": "n28",
      "label": "iKeirNez"
    },
    {
      "id": "n189",
      "label": "recon88"
    },
    {
      "id": "n29",
      "label": "samoatesgames"
    },
    {
      "id": "n188",
      "label": "andfRa"
    },
    {
      "id": "n26",
      "label": "antonaut"
    },
    {
      "id": "n187",
      "label": "SXRWahrheit"
    },
    {
      "id": "n27",
      "label": "Toxic-Waste"
    },
    {
      "id": "n186",
      "label": "microgeek"
    },
    {
      "id": "n24",
      "label": "Afforess"
    },
    {
      "id": "n185",
      "label": "dopeghoti"
    },
    {
      "id": "n25",
      "label": "oloflarsson"
    },
    {
      "id": "n10",
      "label": "riking"
    },
    {
      "id": "n12",
      "label": "fromgate"
    },
    {
      "id": "n11",
      "label": "HeroCC"
    },
    {
      "id": "n17",
      "label": "DziNeIT"
    },
    {
      "id": "n18",
      "label": "asofold"
    },
    {
      "id": "n19",
      "label": "agaricusb"
    },
    {
      "id": "n13",
      "label": "Ju4nD95"
    },
    {
      "id": "n197",
      "label": "Jg23"
    },
    {
      "id": "n14",
      "label": "gmcferrin"
    },
    {
      "id": "n196",
      "label": "SnoFox"
    },
    {
      "id": "n15",
      "label": "toqueteos"
    },
    {
      "id": "n199",
      "label": "lol768"
    },
    {
      "id": "n16",
      "label": "quickwango"
    },
    {
      "id": "n198",
      "label": "Anxuiz"
    },
    {
      "id": "n80",
      "label": "ScoreUnder"
    },
    {
      "id": "n81",
      "label": "Multitallented"
    },
    {
      "id": "n84",
      "label": "OndrejNepozitek"
    },
    {
      "id": "n85",
      "label": "t3hk0d3"
    },
    {
      "id": "n82",
      "label": "durron597"
    },
    {
      "id": "n83",
      "label": "ammaraskar"
    },
    {
      "id": "n88",
      "label": "Denney"
    },
    {
      "id": "n89",
      "label": "acuddlyheadcrab"
    },
    {
      "id": "n86",
      "label": "Dinnerbone"
    },
    {
      "id": "n87",
      "label": "CunningPlan"
    },
    {
      "id": "n121",
      "label": "Fishrock123"
    },
    {
      "id": "n122",
      "label": "shinyquagsire23"
    },
    {
      "id": "n120",
      "label": "Steveice10"
    },
    {
      "id": "n125",
      "label": "darkcloud784"
    },
    {
      "id": "n126",
      "label": "chaseoes"
    },
    {
      "id": "n123",
      "label": "Devil-Boy"
    },
    {
      "id": "n124",
      "label": "DarkArc"
    },
    {
      "id": "n129",
      "label": "AlphaBlend"
    },
    {
      "id": "n127",
      "label": "lishd"
    },
    {
      "id": "n128",
      "label": "hatstand0"
    },
    {
      "id": "n70",
      "label": "xGhOsTkiLLeRx"
    },
    {
      "id": "n71",
      "label": "YLivay"
    },
    {
      "id": "n72",
      "label": "zonedabone"
    },
    {
      "id": "n73",
      "label": "Sablednah"
    },
    {
      "id": "n74",
      "label": "drantor"
    },
    {
      "id": "n75",
      "label": "cybertiger"
    },
    {
      "id": "n76",
      "label": "oliver1610"
    },
    {
      "id": "n140",
      "label": "Pangamma"
    },
    {
      "id": "n77",
      "label": "Artemu"
    },
    {
      "id": "n78",
      "label": "macer1"
    },
    {
      "id": "n130",
      "label": "MisterH"
    },
    {
      "id": "n131",
      "label": "syamn"
    },
    {
      "id": "n79",
      "label": "morganm"
    },
    {
      "id": "n132",
      "label": "Qix-"
    },
    {
      "id": "n133",
      "label": "Blingdaddy1"
    },
    {
      "id": "n134",
      "label": "desht"
    },
    {
      "id": "n135",
      "label": "Ne0nx3r0"
    },
    {
      "id": "n136",
      "label": "jjkoletar"
    },
    {
      "id": "n137",
      "label": "goldblattster"
    },
    {
      "id": "n138",
      "label": "tyrovc"
    },
    {
      "id": "n139",
      "label": "FaustNight"
    },
    {
      "id": "n151",
      "label": "melekaiah"
    },
    {
      "id": "n66",
      "label": "Kainzo"
    },
    {
      "id": "n150",
      "label": "grandwazir"
    },
    {
      "id": "n67",
      "label": "alkarinv"
    },
    {
      "id": "n64",
      "label": "ryantheleach"
    },
    {
      "id": "n65",
      "label": "clucky"
    },
    {
      "id": "n62",
      "label": "mcfacilitator"
    },
    {
      "id": "n63",
      "label": "Technius"
    },
    {
      "id": "n60",
      "label": "Puremin0rez"
    },
    {
      "id": "n61",
      "label": "KaBob799"
    },
    {
      "id": "n147",
      "label": "gravypod"
    },
    {
      "id": "n148",
      "label": "acstache"
    },
    {
      "id": "n145",
      "label": "MasterGabeMOD"
    },
    {
      "id": "n146",
      "label": "YoshiGenius"
    },
    {
      "id": "n143",
      "label": "computerdude5000"
    },
    {
      "id": "n144",
      "label": "stevenh"
    },
    {
      "id": "n141",
      "label": "Xentec"
    },
    {
      "id": "n69",
      "label": "authorblues"
    },
    {
      "id": "n142",
      "label": "mcsnetworks"
    },
    {
      "id": "n68",
      "label": "boduzapho"
    },
    {
      "id": "n149",
      "label": "dumptruckman"
    },
    {
      "id": "n160",
      "label": "Muwbi"
    },
    {
      "id": "n53",
      "label": "LB--"
    },
    {
      "id": "n54",
      "label": "TnTBass"
    },
    {
      "id": "n162",
      "label": "BennehT"
    },
    {
      "id": "n55",
      "label": "XemsDoom"
    },
    {
      "id": "n161",
      "label": "evilmidget38"
    },
    {
      "id": "n56",
      "label": "turt2live"
    },
    {
      "id": "n50",
      "label": "bob7l"
    },
    {
      "id": "n51",
      "label": "dredhorse"
    },
    {
      "id": "n52",
      "label": "bergerkiller"
    },
    {
      "id": "n156",
      "label": "stefansaraev"
    },
    {
      "id": "n157",
      "label": "Dragonphase"
    },
    {
      "id": "n158",
      "label": "DerFlash"
    },
    {
      "id": "n159",
      "label": "spaceemotion"
    },
    {
      "id": "n152",
      "label": "coldandtired"
    },
    {
      "id": "n58",
      "label": "GarretSidzaka"
    },
    {
      "id": "n153",
      "label": "lucasdidur"
    },
    {
      "id": "n57",
      "label": "BillyGalbreath"
    },
    {
      "id": "n154",
      "label": "dddeeefff"
    },
    {
      "id": "n155",
      "label": "ViscousSummer88"
    },
    {
      "id": "n59",
      "label": "CorrieKay"
    },
    {
      "id": "n109",
      "label": "Ndollar123"
    },
    {
      "id": "n106",
      "label": "CelticMinstrel"
    },
    {
      "id": "n105",
      "label": "Lolmen"
    },
    {
      "id": "n108",
      "label": "ambedrake"
    },
    {
      "id": "n107",
      "label": "GrandRiver"
    },
    {
      "id": "n102",
      "label": "latexink"
    },
    {
      "id": "n101",
      "label": "mikeprimm"
    },
    {
      "id": "n104",
      "label": "V10lator"
    },
    {
      "id": "n103",
      "label": "Brettflan"
    },
    {
      "id": "n100",
      "label": "betterphp"
    },
    {
      "id": "n119",
      "label": "LinearLogic"
    },
    {
      "id": "n118",
      "label": "blha303"
    },
    {
      "id": "n117",
      "label": "matepeter"
    },
    {
      "id": "n116",
      "label": "EpicTrance"
    },
    {
      "id": "n115",
      "label": "coelho"
    },
    {
      "id": "n114",
      "label": "Meaglin"
    },
    {
      "id": "n113",
      "label": "Aangiix3"
    },
    {
      "id": "n112",
      "label": "cruzer0"
    },
    {
      "id": "n111",
      "label": "DjDCH"
    },
    {
      "id": "n110",
      "label": "PCXD"
    }
  ],
  "links": [
    {
      "weight": 6.0,
      "id": "19",
      "target": "n3",
      "source": "n54",
      "value": "19"
    },
    {
      "weight": 3.0,
      "id": "35",
      "target": "n121",
      "source": "n375",
      "value": "35"
    },
    {
      "weight": 6.0,
      "id": "17",
      "target": "n3",
      "source": "n96",
      "value": "17"
    },
    {
      "weight": 3.0,
      "id": "36",
      "target": "n20",
      "source": "n358",
      "value": "36"
    },
    {
      "weight": 6.0,
      "id": "18",
      "target": "n3",
      "source": "n6",
      "value": "18"
    },
    {
      "weight": 6.0,
      "id": "33",
      "target": "n2",
      "source": "n20",
      "value": "33"
    },
    {
      "weight": 3.0,
      "id": "15",
      "target": "n4",
      "source": "n8",
      "value": "15"
    },
    {
      "weight": 6.0,
      "id": "34",
      "target": "n61",
      "source": "n104",
      "value": "34"
    },
    {
      "weight": 3.0,
      "id": "16",
      "target": "n3",
      "source": "n95",
      "value": "16"
    },
    {
      "weight": 3.0,
      "id": "39",
      "target": "n129",
      "source": "n384",
      "value": "39"
    },
    {
      "weight": 3.0,
      "id": "13",
      "target": "n8",
      "source": "n87",
      "value": "13"
    },
    {
      "weight": 3.0,
      "id": "14",
      "target": "n8",
      "source": "n88",
      "value": "14"
    },
    {
      "weight": 6.0,
      "id": "37",
      "target": "n1",
      "source": "n358",
      "value": "37"
    },
    {
      "weight": 3.0,
      "id": "11",
      "target": "n3",
      "source": "n78",
      "value": "11"
    },
    {
      "weight": 6.0,
      "id": "38",
      "target": "n1",
      "source": "n300",
      "value": "38"
    },
    {
      "weight": 3.0,
      "id": "12",
      "target": "n3",
      "source": "n22",
      "value": "12"
    },
    {
      "weight": 12.0,
      "id": "21",
      "target": "n3",
      "source": "n4",
      "value": "21"
    },
    {
      "weight": 3.0,
      "id": "20",
      "target": "n3",
      "source": "n100",
      "value": "20"
    },
    {
      "weight": 3.0,
      "id": "43",
      "target": "n121",
      "source": "n335",
      "value": "43"
    },
    {
      "weight": 3.0,
      "id": "42",
      "target": "n335",
      "source": "n430",
      "value": "42"
    },
    {
      "weight": 3.0,
      "id": "41",
      "target": "n20",
      "source": "n300",
      "value": "41"
    },
    {
      "weight": 3.0,
      "id": "40",
      "target": "n61",
      "source": "n300",
      "value": "40"
    },
    {
      "weight": 6.0,
      "id": "49",
      "target": "n20",
      "source": "n297",
      "value": "49"
    },
    {
      "weight": 3.0,
      "id": "48",
      "target": "n2",
      "source": "n297",
      "value": "48"
    },
    {
      "weight": 3.0,
      "id": "45",
      "target": "n104",
      "source": "n121",
      "value": "45"
    },
    {
      "weight": 3.0,
      "id": "44",
      "target": "n20",
      "source": "n335",
      "value": "44"
    },
    {
      "weight": 3.0,
      "id": "47",
      "target": "n121",
      "source": "n129",
      "value": "47"
    },
    {
      "weight": 3.0,
      "id": "46",
      "target": "n129",
      "source": "n438",
      "value": "46"
    },
    {
      "weight": 3.0,
      "id": "22",
      "target": "n3",
      "source": "n101",
      "value": "22"
    },
    {
      "weight": 6.0,
      "id": "23",
      "target": "n3",
      "source": "n184",
      "value": "23"
    },
    {
      "weight": 3.0,
      "id": "24",
      "target": "n3",
      "source": "n86",
      "value": "24"
    },
    {
      "weight": 6.0,
      "id": "25",
      "target": "n3",
      "source": "n221",
      "value": "25"
    },
    {
      "weight": 3.0,
      "id": "26",
      "target": "n3",
      "source": "n222",
      "value": "26"
    },
    {
      "weight": 3.0,
      "id": "27",
      "target": "n3",
      "source": "n47",
      "value": "27"
    },
    {
      "weight": 6.0,
      "id": "28",
      "target": "n2",
      "source": "n300",
      "value": "28"
    },
    {
      "weight": 12.0,
      "id": "29",
      "target": "n8",
      "source": "n104",
      "value": "29"
    },
    {
      "weight": 3.0,
      "id": "3",
      "target": "n2",
      "source": "n6",
      "value": "3"
    },
    {
      "weight": 3.0,
      "id": "2",
      "target": "n2",
      "source": "n5",
      "value": "2"
    },
    {
      "weight": 3.0,
      "id": "10",
      "target": "n3",
      "source": "n8",
      "value": "10"
    },
    {
      "weight": 9.0,
      "id": "1",
      "target": "n2",
      "source": "n4",
      "value": "1"
    },
    {
      "weight": 9.0,
      "id": "0",
      "target": "n2",
      "source": "n3",
      "value": "0"
    },
    {
      "weight": 15.0,
      "id": "30",
      "target": "n2",
      "source": "n104",
      "value": "30"
    },
    {
      "weight": 6.0,
      "id": "7",
      "target": "n2",
      "source": "n41",
      "value": "7"
    },
    {
      "weight": 6.0,
      "id": "6",
      "target": "n2",
      "source": "n16",
      "value": "6"
    },
    {
      "weight": 12.0,
      "id": "32",
      "target": "n2",
      "source": "n10",
      "value": "32"
    },
    {
      "weight": 3.0,
      "id": "5",
      "target": "n8",
      "source": "n9",
      "value": "5"
    },
    {
      "weight": 9.0,
      "id": "31",
      "target": "n10",
      "source": "n121",
      "value": "31"
    },
    {
      "weight": 6.0,
      "id": "4",
      "target": "n7",
      "source": "n8",
      "value": "4"
    },
    {
      "weight": 9.0,
      "id": "9",
      "target": "n1",
      "source": "n3",
      "value": "9"
    },
    {
      "weight": 3.0,
      "id": "8",
      "target": "n3",
      "source": "n61",
      "value": "8"
    }
  ]
}
