{
  "nodes": [
    {
      "id": "n41",
      "label": "bncoelho"
    },
    {
      "id": "n40",
      "label": "thatRD"
    },
    {
      "id": "n45",
      "label": "brow"
    },
    {
      "id": "n44",
      "label": "brunohenrique"
    },
    {
      "id": "n43",
      "label": "landtax"
    },
    {
      "id": "n42",
      "label": "Quantisan"
    },
    {
      "id": "n92",
      "label": "mattfield"
    },
    {
      "id": "n91",
      "label": "unindented"
    },
    {
      "id": "n90",
      "label": "elitalon"
    },
    {
      "id": "n96",
      "label": "tub78"
    },
    {
      "id": "n48",
      "label": "a-b"
    },
    {
      "id": "n49",
      "label": "robertomiranda"
    },
    {
      "id": "n95",
      "label": "jofi"
    },
    {
      "id": "n46",
      "label": "jaredonline"
    },
    {
      "id": "n94",
      "label": "johnhampton"
    },
    {
      "id": "n47",
      "label": "moutten"
    },
    {
      "id": "n93",
      "label": "billcarroll"
    },
    {
      "id": "n99",
      "label": "rdlugosz"
    },
    {
      "id": "n98",
      "label": "tecnobrat"
    },
    {
      "id": "n97",
      "label": "randy86v"
    },
    {
      "id": "n30",
      "label": "trungie"
    },
    {
      "id": "n32",
      "label": "aktagon"
    },
    {
      "id": "n31",
      "label": "guilleiguaran"
    },
    {
      "id": "n34",
      "label": "richardkmichael"
    },
    {
      "id": "n33",
      "label": "duboisf"
    },
    {
      "id": "n35",
      "label": "bagilevi"
    },
    {
      "id": "n36",
      "label": "rafmagana"
    },
    {
      "id": "n37",
      "label": "pkmishra"
    },
    {
      "id": "n38",
      "label": "tomekw"
    },
    {
      "id": "n39",
      "label": "vassilevsky"
    },
    {
      "id": "n1",
      "label": "olek"
    },
    {
      "id": "n23",
      "label": "flebber"
    },
    {
      "id": "n0",
      "label": "eMxyzptlk"
    },
    {
      "id": "n22",
      "label": "jess"
    },
    {
      "id": "n21",
      "label": "readmedia"
    },
    {
      "id": "n20",
      "label": "matt-holden"
    },
    {
      "id": "n5",
      "label": "helps"
    },
    {
      "id": "n4",
      "label": "hellerbarde"
    },
    {
      "id": "n3",
      "label": "adrianrego"
    },
    {
      "id": "n2",
      "label": "gagoar"
    },
    {
      "id": "n102",
      "label": "reinh"
    },
    {
      "id": "n9",
      "label": "williamherry"
    },
    {
      "id": "n101",
      "label": "glennr"
    },
    {
      "id": "n8",
      "label": "stantonk"
    },
    {
      "id": "n7",
      "label": "sul3n3t"
    },
    {
      "id": "n103",
      "label": "pjg"
    },
    {
      "id": "n6",
      "label": "eQu1NoX"
    },
    {
      "id": "n100",
      "label": "evandavey"
    },
    {
      "id": "n28",
      "label": "tpope"
    },
    {
      "id": "n29",
      "label": "mrooney"
    },
    {
      "id": "n26",
      "label": "Kache"
    },
    {
      "id": "n27",
      "label": "ssfrr"
    },
    {
      "id": "n24",
      "label": "sdhull"
    },
    {
      "id": "n25",
      "label": "robsonpeixoto"
    },
    {
      "id": "n10",
      "label": "olalonde"
    },
    {
      "id": "n12",
      "label": "rosstimson"
    },
    {
      "id": "n11",
      "label": "theirishpenguin"
    },
    {
      "id": "n17",
      "label": "dfischer"
    },
    {
      "id": "n18",
      "label": "jasonschock"
    },
    {
      "id": "n19",
      "label": "rking"
    },
    {
      "id": "n13",
      "label": "barumrho"
    },
    {
      "id": "n14",
      "label": "alexmuller"
    },
    {
      "id": "n15",
      "label": "bsodmike"
    },
    {
      "id": "n16",
      "label": "cakephemist"
    },
    {
      "id": "n80",
      "label": "stephanvd"
    },
    {
      "id": "n81",
      "label": "hms"
    },
    {
      "id": "n84",
      "label": "csage"
    },
    {
      "id": "n85",
      "label": "vzemlyansky"
    },
    {
      "id": "n82",
      "label": "pydave"
    },
    {
      "id": "n83",
      "label": "noefroidevaux"
    },
    {
      "id": "n88",
      "label": "kebot"
    },
    {
      "id": "n89",
      "label": "mechanicles"
    },
    {
      "id": "n86",
      "label": "chickenchan"
    },
    {
      "id": "n87",
      "label": "tonylotts"
    },
    {
      "id": "n70",
      "label": "mrichman"
    },
    {
      "id": "n71",
      "label": "tjstankus"
    },
    {
      "id": "n72",
      "label": "henrymazza"
    },
    {
      "id": "n73",
      "label": "pcragone"
    },
    {
      "id": "n74",
      "label": "chetan"
    },
    {
      "id": "n75",
      "label": "jmcollis"
    },
    {
      "id": "n76",
      "label": "jeroendv"
    },
    {
      "id": "n77",
      "label": "bijzz"
    },
    {
      "id": "n78",
      "label": "dcalacci"
    },
    {
      "id": "n79",
      "label": "kevinpauli"
    },
    {
      "id": "n66",
      "label": "kbg2003"
    },
    {
      "id": "n67",
      "label": "nikhilbhardwaj"
    },
    {
      "id": "n64",
      "label": "kien"
    },
    {
      "id": "n65",
      "label": "collegeimprovements"
    },
    {
      "id": "n62",
      "label": "stefanfrede"
    },
    {
      "id": "n63",
      "label": "jzempel"
    },
    {
      "id": "n60",
      "label": "santoshw"
    },
    {
      "id": "n61",
      "label": "jbylsma"
    },
    {
      "id": "n69",
      "label": "schleppy"
    },
    {
      "id": "n68",
      "label": "ldenman"
    },
    {
      "id": "n53",
      "label": "devinus"
    },
    {
      "id": "n54",
      "label": "phuongnd08"
    },
    {
      "id": "n55",
      "label": "nblumoe"
    },
    {
      "id": "n56",
      "label": "kenton"
    },
    {
      "id": "n50",
      "label": "galtenberg"
    },
    {
      "id": "n51",
      "label": "robi-wan"
    },
    {
      "id": "n52",
      "label": "bitboxer"
    },
    {
      "id": "n58",
      "label": "rey-wright"
    },
    {
      "id": "n57",
      "label": "tfnico"
    },
    {
      "id": "n59",
      "label": "dukedave"
    }
  ],
  "links": [
    {
      "weight": 2.0,
      "id": "35",
      "target": "n0",
      "source": "n41",
      "value": "35"
    },
    {
      "weight": 2.0,
      "id": "36",
      "target": "n0",
      "source": "n42",
      "value": "36"
    },
    {
      "weight": 2.0,
      "id": "33",
      "target": "n0",
      "source": "n39",
      "value": "33"
    },
    {
      "weight": 1.0,
      "id": "34",
      "target": "n0",
      "source": "n40",
      "value": "34"
    },
    {
      "weight": 1.0,
      "id": "39",
      "target": "n0",
      "source": "n45",
      "value": "39"
    },
    {
      "weight": 2.0,
      "id": "37",
      "target": "n0",
      "source": "n43",
      "value": "37"
    },
    {
      "weight": 4.0,
      "id": "38",
      "target": "n0",
      "source": "n44",
      "value": "38"
    },
    {
      "weight": 1.0,
      "id": "43",
      "target": "n0",
      "source": "n49",
      "value": "43"
    },
    {
      "weight": 1.0,
      "id": "42",
      "target": "n0",
      "source": "n48",
      "value": "42"
    },
    {
      "weight": 1.0,
      "id": "41",
      "target": "n0",
      "source": "n47",
      "value": "41"
    },
    {
      "weight": 1.0,
      "id": "40",
      "target": "n0",
      "source": "n46",
      "value": "40"
    },
    {
      "weight": 11.0,
      "id": "22",
      "target": "n0",
      "source": "n28",
      "value": "22"
    },
    {
      "weight": 3.0,
      "id": "23",
      "target": "n0",
      "source": "n29",
      "value": "23"
    },
    {
      "weight": 6.0,
      "id": "24",
      "target": "n3",
      "source": "n30",
      "value": "24"
    },
    {
      "weight": 4.0,
      "id": "25",
      "target": "n0",
      "source": "n31",
      "value": "25"
    },
    {
      "weight": 3.0,
      "id": "26",
      "target": "n0",
      "source": "n32",
      "value": "26"
    },
    {
      "weight": 3.0,
      "id": "27",
      "target": "n0",
      "source": "n33",
      "value": "27"
    },
    {
      "weight": 9.0,
      "id": "28",
      "target": "n0",
      "source": "n34",
      "value": "28"
    },
    {
      "weight": 1.0,
      "id": "29",
      "target": "n0",
      "source": "n35",
      "value": "29"
    },
    {
      "weight": 2.0,
      "id": "3",
      "target": "n0",
      "source": "n5",
      "value": "3"
    },
    {
      "weight": 6.0,
      "id": "2",
      "target": "n3",
      "source": "n4",
      "value": "2"
    },
    {
      "weight": 6.0,
      "id": "1",
      "target": "n0",
      "source": "n2",
      "value": "1"
    },
    {
      "weight": 18.0,
      "id": "0",
      "target": "n0",
      "source": "n1",
      "value": "0"
    },
    {
      "weight": 4.0,
      "id": "30",
      "target": "n0",
      "source": "n36",
      "value": "30"
    },
    {
      "weight": 2.0,
      "id": "7",
      "target": "n3",
      "source": "n10",
      "value": "7"
    },
    {
      "weight": 2.0,
      "id": "6",
      "target": "n0",
      "source": "n9",
      "value": "6"
    },
    {
      "weight": 2.0,
      "id": "32",
      "target": "n0",
      "source": "n38",
      "value": "32"
    },
    {
      "weight": 2.0,
      "id": "5",
      "target": "n0",
      "source": "n8",
      "value": "5"
    },
    {
      "weight": 8.0,
      "id": "31",
      "target": "n0",
      "source": "n37",
      "value": "31"
    },
    {
      "weight": 8.0,
      "id": "4",
      "target": "n0",
      "source": "n7",
      "value": "4"
    },
    {
      "weight": 2.0,
      "id": "9",
      "target": "n0",
      "source": "n15",
      "value": "9"
    },
    {
      "weight": 1.0,
      "id": "8",
      "target": "n0",
      "source": "n14",
      "value": "8"
    },
    {
      "weight": 9.0,
      "id": "19",
      "target": "n3",
      "source": "n25",
      "value": "19"
    },
    {
      "weight": 2.0,
      "id": "17",
      "target": "n0",
      "source": "n23",
      "value": "17"
    },
    {
      "weight": 7.0,
      "id": "18",
      "target": "n0",
      "source": "n24",
      "value": "18"
    },
    {
      "weight": 3.0,
      "id": "15",
      "target": "n0",
      "source": "n21",
      "value": "15"
    },
    {
      "weight": 2.0,
      "id": "16",
      "target": "n0",
      "source": "n22",
      "value": "16"
    },
    {
      "weight": 2.0,
      "id": "13",
      "target": "n0",
      "source": "n19",
      "value": "13"
    },
    {
      "weight": 6.0,
      "id": "14",
      "target": "n3",
      "source": "n20",
      "value": "14"
    },
    {
      "weight": 2.0,
      "id": "11",
      "target": "n0",
      "source": "n17",
      "value": "11"
    },
    {
      "weight": 4.0,
      "id": "12",
      "target": "n0",
      "source": "n18",
      "value": "12"
    },
    {
      "weight": 4.0,
      "id": "21",
      "target": "n0",
      "source": "n27",
      "value": "21"
    },
    {
      "weight": 1.0,
      "id": "20",
      "target": "n0",
      "source": "n26",
      "value": "20"
    },
    {
      "weight": 1.0,
      "id": "108",
      "target": "n22",
      "source": "n76",
      "value": "108"
    },
    {
      "weight": 1.0,
      "id": "107",
      "target": "n27",
      "source": "n103",
      "value": "107"
    },
    {
      "weight": 1.0,
      "id": "106",
      "target": "n13",
      "source": "n76",
      "value": "106"
    },
    {
      "weight": 2.0,
      "id": "105",
      "target": "n28",
      "source": "n102",
      "value": "105"
    },
    {
      "weight": 1.0,
      "id": "104",
      "target": "n28",
      "source": "n101",
      "value": "104"
    },
    {
      "weight": 1.0,
      "id": "103",
      "target": "n99",
      "source": "n100",
      "value": "103"
    },
    {
      "weight": 1.0,
      "id": "102",
      "target": "n90",
      "source": "n98",
      "value": "102"
    },
    {
      "weight": 2.0,
      "id": "99",
      "target": "n22",
      "source": "n96",
      "value": "99"
    },
    {
      "weight": 1.0,
      "id": "101",
      "target": "n0",
      "source": "n97",
      "value": "101"
    },
    {
      "weight": 1.0,
      "id": "100",
      "target": "n22",
      "source": "n45",
      "value": "100"
    },
    {
      "weight": 2.0,
      "id": "98",
      "target": "n9",
      "source": "n76",
      "value": "98"
    },
    {
      "weight": 1.0,
      "id": "97",
      "target": "n0",
      "source": "n13",
      "value": "97"
    },
    {
      "weight": 1.0,
      "id": "96",
      "target": "n48",
      "source": "n53",
      "value": "96"
    },
    {
      "weight": 4.0,
      "id": "95",
      "target": "n73",
      "source": "n95",
      "value": "95"
    },
    {
      "weight": 1.0,
      "id": "94",
      "target": "n0",
      "source": "n94",
      "value": "94"
    },
    {
      "weight": 1.0,
      "id": "93",
      "target": "n57",
      "source": "n93",
      "value": "93"
    },
    {
      "weight": 1.0,
      "id": "92",
      "target": "n76",
      "source": "n79",
      "value": "92"
    },
    {
      "weight": 3.0,
      "id": "91",
      "target": "n0",
      "source": "n30",
      "value": "91"
    },
    {
      "weight": 3.0,
      "id": "90",
      "target": "n52",
      "source": "n92",
      "value": "90"
    },
    {
      "weight": 2.0,
      "id": "10",
      "target": "n0",
      "source": "n16",
      "value": "10"
    },
    {
      "weight": 1.0,
      "id": "88",
      "target": "n89",
      "source": "n90",
      "value": "88"
    },
    {
      "weight": 1.0,
      "id": "89",
      "target": "n57",
      "source": "n91",
      "value": "89"
    },
    {
      "weight": 1.0,
      "id": "79",
      "target": "n57",
      "source": "n83",
      "value": "79"
    },
    {
      "weight": 2.0,
      "id": "78",
      "target": "n60",
      "source": "n82",
      "value": "78"
    },
    {
      "weight": 1.0,
      "id": "77",
      "target": "n18",
      "source": "n81",
      "value": "77"
    },
    {
      "weight": 1.0,
      "id": "82",
      "target": "n0",
      "source": "n79",
      "value": "82"
    },
    {
      "weight": 1.0,
      "id": "83",
      "target": "n40",
      "source": "n57",
      "value": "83"
    },
    {
      "weight": 2.0,
      "id": "80",
      "target": "n18",
      "source": "n84",
      "value": "80"
    },
    {
      "weight": 1.0,
      "id": "81",
      "target": "n0",
      "source": "n53",
      "value": "81"
    },
    {
      "weight": 1.0,
      "id": "86",
      "target": "n57",
      "source": "n87",
      "value": "86"
    },
    {
      "weight": 1.0,
      "id": "87",
      "target": "n21",
      "source": "n88",
      "value": "87"
    },
    {
      "weight": 1.0,
      "id": "84",
      "target": "n18",
      "source": "n85",
      "value": "84"
    },
    {
      "weight": 1.0,
      "id": "85",
      "target": "n21",
      "source": "n86",
      "value": "85"
    },
    {
      "weight": 1.0,
      "id": "67",
      "target": "n39",
      "source": "n73",
      "value": "67"
    },
    {
      "weight": 4.0,
      "id": "66",
      "target": "n0",
      "source": "n72",
      "value": "66"
    },
    {
      "weight": 1.0,
      "id": "69",
      "target": "n21",
      "source": "n75",
      "value": "69"
    },
    {
      "weight": 1.0,
      "id": "68",
      "target": "n18",
      "source": "n74",
      "value": "68"
    },
    {
      "weight": 3.0,
      "id": "70",
      "target": "n57",
      "source": "n76",
      "value": "70"
    },
    {
      "weight": 1.0,
      "id": "71",
      "target": "n0",
      "source": "n57",
      "value": "71"
    },
    {
      "weight": 3.0,
      "id": "72",
      "target": "n0",
      "source": "n76",
      "value": "72"
    },
    {
      "weight": 1.0,
      "id": "73",
      "target": "n76",
      "source": "n77",
      "value": "73"
    },
    {
      "weight": 1.0,
      "id": "74",
      "target": "n78",
      "source": "n79",
      "value": "74"
    },
    {
      "weight": 3.0,
      "id": "75",
      "target": "n12",
      "source": "n62",
      "value": "75"
    },
    {
      "weight": 2.0,
      "id": "76",
      "target": "n18",
      "source": "n80",
      "value": "76"
    },
    {
      "weight": 3.0,
      "id": "59",
      "target": "n0",
      "source": "n54",
      "value": "59"
    },
    {
      "weight": 9.0,
      "id": "58",
      "target": "n20",
      "source": "n64",
      "value": "58"
    },
    {
      "weight": 3.0,
      "id": "57",
      "target": "n52",
      "source": "n63",
      "value": "57"
    },
    {
      "weight": 3.0,
      "id": "56",
      "target": "n29",
      "source": "n62",
      "value": "56"
    },
    {
      "weight": 3.0,
      "id": "55",
      "target": "n0",
      "source": "n61",
      "value": "55"
    },
    {
      "weight": 2.0,
      "id": "64",
      "target": "n18",
      "source": "n70",
      "value": "64"
    },
    {
      "weight": 1.0,
      "id": "65",
      "target": "n22",
      "source": "n71",
      "value": "65"
    },
    {
      "weight": 9.0,
      "id": "62",
      "target": "n52",
      "source": "n68",
      "value": "62"
    },
    {
      "weight": 1.0,
      "id": "63",
      "target": "n21",
      "source": "n69",
      "value": "63"
    },
    {
      "weight": 1.0,
      "id": "60",
      "target": "n22",
      "source": "n57",
      "value": "60"
    },
    {
      "weight": 3.0,
      "id": "61",
      "target": "n0",
      "source": "n20",
      "value": "61"
    },
    {
      "weight": 2.0,
      "id": "49",
      "target": "n0",
      "source": "n55",
      "value": "49"
    },
    {
      "weight": 3.0,
      "id": "48",
      "target": "n3",
      "source": "n54",
      "value": "48"
    },
    {
      "weight": 2.0,
      "id": "45",
      "target": "n0",
      "source": "n51",
      "value": "45"
    },
    {
      "weight": 2.0,
      "id": "44",
      "target": "n0",
      "source": "n50",
      "value": "44"
    },
    {
      "weight": 1.0,
      "id": "47",
      "target": "n44",
      "source": "n53",
      "value": "47"
    },
    {
      "weight": 3.0,
      "id": "46",
      "target": "n3",
      "source": "n52",
      "value": "46"
    },
    {
      "weight": 3.0,
      "id": "51",
      "target": "n3",
      "source": "n58",
      "value": "51"
    },
    {
      "weight": 9.0,
      "id": "52",
      "target": "n0",
      "source": "n58",
      "value": "52"
    },
    {
      "weight": 2.0,
      "id": "53",
      "target": "n3",
      "source": "n17",
      "value": "53"
    },
    {
      "weight": 1.0,
      "id": "54",
      "target": "n59",
      "source": "n60",
      "value": "54"
    },
    {
      "weight": 1.0,
      "id": "50",
      "target": "n56",
      "source": "n57",
      "value": "50"
    }
  ]
}
